{
  "annotations": [
    {
      "bounding_box": {
        "h": 24.88000000000001,
        "w": 21.689999999999998,
        "x": 143.28,
        "y": 95.13
      },
      "id": "384001e4-5192-4922-8dc9-0e8ef7cbb2dc",
      "name": "Leaf",
      "polygon": {
        "path": [
          {
            "x": 164.97,
            "y": 108.94
          },
          {
            "x": 163.19,
            "y": 98.26
          },
          {
            "x": 161.15,
            "y": 95.99
          },
          {
            "x": 158.23,
            "y": 95.13
          },
          {
            "x": 152.8,
            "y": 95.76
          },
          {
            "x": 145.05,
            "y": 101.0
          },
          {
            "x": 143.28,
            "y": 106.2
          },
          {
            "x": 143.69,
            "y": 109.8
          },
          {
            "x": 145.96,
            "y": 112.98
          },
          {
            "x": 151.48,
            "y": 116.09
          },
          {
            "x": 151.67,
            "y": 118.47
          },
          {
            "x": 152.8,
            "y": 119.6
          },
          {
            "x": 155.26,
            "y": 120.01
          },
          {
            "x": 160.0,
            "y": 118.69
          },
          {
            "x": 162.28,
            "y": 116.64
          },
          {
            "x": 164.97,
            "y": 108.94
          }
        ]
      }
    },
    {
      "bounding_box": {
        "h": 20.78,
        "w": 24.89,
        "x": 106.55,
        "y": 137.55
      },
      "id": "e2fa0e94-adeb-45eb-a1dd-3f95d267df46",
      "name": "Leaf",
      "polygon": {
        "path": [
          {
            "x": 131.44,
            "y": 148.17
          },
          {
            "x": 129.89,
            "y": 141.83
          },
          {
            "x": 128.53,
            "y": 140.47
          },
          {
            "x": 126.44,
            "y": 140.2
          },
          {
            "x": 122.6,
            "y": 138.19
          },
          {
            "x": 118.54,
            "y": 137.55
          },
          {
            "x": 115.39,
            "y": 137.96
          },
          {
            "x": 112.66,
            "y": 139.56
          },
          {
            "x": 107.88,
            "y": 145.02
          },
          {
            "x": 106.55,
            "y": 152.5
          },
          {
            "x": 107.19,
            "y": 155.42
          },
          {
            "x": 108.32,
            "y": 156.55
          },
          {
            "x": 114.43,
            "y": 158.33
          },
          {
            "x": 124.66,
            "y": 157.63
          },
          {
            "x": 128.06,
            "y": 154.74
          },
          {
            "x": 131.44,
            "y": 148.17
          }
        ]
      }
    },
    {
      "bounding_box": {
        "h": 13.709999999999994,
        "w": 15.299999999999983,
        "x": 126.4,
        "y": 122.27
      },
      "id": "ab96deae-6af8-491c-8fbe-ba905ce07d2c",
      "name": "Leaf",
      "polygon": {
        "path": [
          {
            "x": 141.7,
            "y": 128.1
          },
          {
            "x": 141.29,
            "y": 126.55
          },
          {
            "x": 139.02,
            "y": 124.05
          },
          {
            "x": 133.36,
            "y": 122.27
          },
          {
            "x": 130.45,
            "y": 122.68
          },
          {
            "x": 128.62,
            "y": 123.82
          },
          {
            "x": 127.04,
            "y": 125.63
          },
          {
            "x": 126.4,
            "y": 127.87
          },
          {
            "x": 126.81,
            "y": 130.56
          },
          {
            "x": 130.45,
            "y": 134.43
          },
          {
            "x": 135.87,
            "y": 135.98
          },
          {
            "x": 137.88,
            "y": 135.57
          },
          {
            "x": 139.01,
            "y": 134.44
          },
          {
            "x": 141.29,
            "y": 129.65
          }
        ]
      }
    },
    {
      "bounding_box": {
        "h": 7.090000000000003,
        "w": 10.969999999999999,
        "x": 128.91,
        "y": 116.11
      },
      "id": "24ea38ee-6048-44cc-9dcf-c835c31599be",
      "name": "Leaf",
      "polygon": {
        "path": [
          {
            "x": 139.88,
            "y": 120.11
          },
          {
            "x": 139.47,
            "y": 118.11
          },
          {
            "x": 135.87,
            "y": 116.11
          },
          {
            "x": 130.45,
            "y": 116.98
          },
          {
            "x": 128.91,
            "y": 119.66
          },
          {
            "x": 129.32,
            "y": 121.43
          },
          {
            "x": 132.0,
            "y": 122.97
          },
          {
            "x": 134.01,
            "y": 122.56
          },
          {
            "x": 136.79,
            "y": 123.2
          },
          {
            "x": 139.47,
            "y": 121.66
          }
        ]
      }
    },
    {
      "bounding_box": {
        "h": 19.180000000000007,
        "w": 13.70999999999998,
        "x": 141.68,
        "y": 138.01
      },
      "id": "a6091af9-75e6-4e1d-9bdc-7f1f465adeda",
      "name": "Leaf",
      "polygon": {
        "path": [
          {
            "x": 155.39,
            "y": 147.94
          },
          {
            "x": 154.98,
            "y": 145.25
          },
          {
            "x": 152.92,
            "y": 140.92
          },
          {
            "x": 149.97,
            "y": 138.42
          },
          {
            "x": 147.96,
            "y": 138.01
          },
          {
            "x": 145.96,
            "y": 138.42
          },
          {
            "x": 142.32,
            "y": 142.51
          },
          {
            "x": 141.68,
            "y": 146.57
          },
          {
            "x": 142.09,
            "y": 150.86
          },
          {
            "x": 147.55,
            "y": 156.78
          },
          {
            "x": 149.33,
            "y": 157.19
          },
          {
            "x": 151.79,
            "y": 156.32
          },
          {
            "x": 153.38,
            "y": 154.51
          },
          {
            "x": 155.39,
            "y": 147.94
          }
        ]
      }
    },
    {
      "bounding_box": {
        "h": 10.289999999999992,
        "w": 9.829999999999984,
        "x": 145.33,
        "y": 126.37
      },
      "id": "32c6c6d2-1bd7-471e-80b7-73b8a53e4ca6",
      "name": "Leaf",
      "polygon": {
        "path": [
          {
            "x": 155.16,
            "y": 131.97
          },
          {
            "x": 154.52,
            "y": 128.14
          },
          {
            "x": 153.39,
            "y": 127.01
          },
          {
            "x": 150.93,
            "y": 126.37
          },
          {
            "x": 148.24,
            "y": 127.01
          },
          {
            "x": 145.74,
            "y": 129.51
          },
          {
            "x": 145.33,
            "y": 131.29
          },
          {
            "x": 147.11,
            "y": 135.12
          },
          {
            "x": 149.79,
            "y": 136.66
          },
          {
            "x": 152.71,
            "y": 136.02
          },
          {
            "x": 154.29,
            "y": 134.44
          },
          {
            "x": 155.16,
            "y": 131.97
          }
        ]
      }
    },
    {
      "bounding_box": {
        "h": 12.609999999999985,
        "w": 8.009999999999991,
        "x": 154.22,
        "y": 140.06
      },
      "id": "379eb574-2e4b-4d91-9aac-fa0da3cb0392",
      "name": "Leaf",
      "polygon": {
        "path": [
          {
            "x": 162.23,
            "y": 145.43
          },
          {
            "x": 159.09,
            "y": 140.47
          },
          {
            "x": 157.31,
            "y": 140.06
          },
          {
            "x": 154.63,
            "y": 141.6
          },
          {
            "x": 154.22,
            "y": 143.15
          },
          {
            "x": 155.36,
            "y": 147.48
          },
          {
            "x": 154.45,
            "y": 149.99
          },
          {
            "x": 155.99,
            "y": 152.67
          },
          {
            "x": 159.09,
            "y": 152.67
          },
          {
            "x": 161.13,
            "y": 149.95
          },
          {
            "x": 161.82,
            "y": 146.98
          }
        ]
      }
    }
  ],
  "dataset": "leafSegmentationPhenovator",
  "image": {
    "filename": "32-18-new_Tray-3x3_120-FC1-FcParamImage-Fmp_2.png",
    "height": 266,
    "original_filename": "32-18-new_Tray-3x3_120-FC1-FcParamImage-Fmp_2.png",
    "path": "/",
    "thumbnail_url": "https://darwin.v7labs.com/api/images/379952877/thumbnail",
    "url": "https://darwin.v7labs.com/api/images/379952877/original",
    "width": 266,
    "workview_url": "https://darwin.v7labs.com/workview?dataset=470301&image=265"
  }
}