{
  "annotations": [
    {
      "bounding_box": {
        "h": 28.0,
        "w": 26.0,
        "x": 134.0,
        "y": 96.0
      },
      "id": "3f35b283-08d9-4fa5-b8dc-90c86bf5ac49",
      "name": "Leaf",
      "polygon": {
        "path": [
          {
            "x": 143.0,
            "y": 96.0
          },
          {
            "x": 139.0,
            "y": 99.0
          },
          {
            "x": 138.0,
            "y": 99.0
          },
          {
            "x": 134.0,
            "y": 106.0
          },
          {
            "x": 134.0,
            "y": 116.0
          },
          {
            "x": 138.0,
            "y": 121.0
          },
          {
            "x": 144.0,
            "y": 124.0
          },
          {
            "x": 146.0,
            "y": 123.0
          },
          {
            "x": 154.0,
            "y": 123.0
          },
          {
            "x": 156.0,
            "y": 122.0
          },
          {
            "x": 158.0,
            "y": 120.0
          },
          {
            "x": 158.0,
            "y": 118.0
          },
          {
            "x": 160.0,
            "y": 114.0
          },
          {
            "x": 160.0,
            "y": 109.0
          },
          {
            "x": 159.0,
            "y": 108.0
          },
          {
            "x": 159.0,
            "y": 105.0
          },
          {
            "x": 157.0,
            "y": 101.0
          },
          {
            "x": 153.0,
            "y": 97.0
          },
          {
            "x": 151.0,
            "y": 97.0
          },
          {
            "x": 150.0,
            "y": 96.0
          }
        ]
      }
    },
    {
      "bounding_box": {
        "h": 18.0,
        "w": 15.0,
        "x": 148.0,
        "y": 126.0
      },
      "id": "b90015e6-576f-4b46-af6d-4cc9d91b69e8",
      "name": "Leaf",
      "polygon": {
        "path": [
          {
            "x": 159.0,
            "y": 126.0
          },
          {
            "x": 156.0,
            "y": 126.0
          },
          {
            "x": 152.0,
            "y": 128.0
          },
          {
            "x": 152.0,
            "y": 129.0
          },
          {
            "x": 149.0,
            "y": 132.0
          },
          {
            "x": 148.0,
            "y": 134.0
          },
          {
            "x": 148.0,
            "y": 138.0
          },
          {
            "x": 149.0,
            "y": 139.0
          },
          {
            "x": 150.0,
            "y": 144.0
          },
          {
            "x": 152.0,
            "y": 143.0
          },
          {
            "x": 153.0,
            "y": 144.0
          },
          {
            "x": 158.0,
            "y": 144.0
          },
          {
            "x": 163.0,
            "y": 141.0
          },
          {
            "x": 163.0,
            "y": 138.0
          },
          {
            "x": 162.0,
            "y": 137.0
          },
          {
            "x": 162.0,
            "y": 131.0
          },
          {
            "x": 161.0,
            "y": 130.0
          },
          {
            "x": 161.0,
            "y": 128.0
          }
        ]
      }
    },
    {
      "bounding_box": {
        "h": 13.0,
        "w": 15.0,
        "x": 135.0,
        "y": 138.0
      },
      "id": "77acfbad-7956-48e1-abb5-f1333ef12334",
      "name": "Leaf",
      "polygon": {
        "path": [
          {
            "x": 135.0,
            "y": 143.0
          },
          {
            "x": 138.0,
            "y": 149.0
          },
          {
            "x": 140.0,
            "y": 151.0
          },
          {
            "x": 142.0,
            "y": 151.0
          },
          {
            "x": 143.0,
            "y": 150.0
          },
          {
            "x": 150.0,
            "y": 150.0
          },
          {
            "x": 149.0,
            "y": 148.0
          },
          {
            "x": 150.0,
            "y": 147.0
          },
          {
            "x": 150.0,
            "y": 141.0
          },
          {
            "x": 149.0,
            "y": 141.0
          },
          {
            "x": 147.0,
            "y": 138.0
          },
          {
            "x": 140.0,
            "y": 138.0
          },
          {
            "x": 140.0,
            "y": 142.0
          },
          {
            "x": 139.0,
            "y": 143.0
          }
        ]
      }
    },
    {
      "bounding_box": {
        "h": 13.0,
        "w": 14.0,
        "x": 130.0,
        "y": 131.0
      },
      "id": "d569b22e-e254-436a-ba4f-e51917018259",
      "name": "Leaf",
      "polygon": {
        "path": [
          {
            "x": 140.0,
            "y": 131.0
          },
          {
            "x": 137.0,
            "y": 131.0
          },
          {
            "x": 133.0,
            "y": 134.0
          },
          {
            "x": 132.0,
            "y": 134.0
          },
          {
            "x": 130.0,
            "y": 136.0
          },
          {
            "x": 130.0,
            "y": 141.0
          },
          {
            "x": 133.0,
            "y": 144.0
          },
          {
            "x": 134.0,
            "y": 144.0
          },
          {
            "x": 136.0,
            "y": 142.0
          },
          {
            "x": 140.0,
            "y": 142.0
          },
          {
            "x": 140.0,
            "y": 140.0
          },
          {
            "x": 141.0,
            "y": 139.0
          },
          {
            "x": 143.0,
            "y": 139.0
          },
          {
            "x": 144.0,
            "y": 137.0
          },
          {
            "x": 142.0,
            "y": 133.0
          }
        ]
      }
    },
    {
      "bounding_box": {
        "h": 22.0,
        "w": 25.0,
        "x": 143.0,
        "y": 155.0
      },
      "id": "977016f5-5383-4c5c-bde0-bb191aa470cd",
      "name": "Leaf",
      "polygon": {
        "path": [
          {
            "x": 144.0,
            "y": 162.0
          },
          {
            "x": 143.0,
            "y": 164.0
          },
          {
            "x": 144.0,
            "y": 171.0
          },
          {
            "x": 146.0,
            "y": 173.0
          },
          {
            "x": 146.0,
            "y": 174.0
          },
          {
            "x": 147.0,
            "y": 174.0
          },
          {
            "x": 149.0,
            "y": 176.0
          },
          {
            "x": 151.0,
            "y": 176.0
          },
          {
            "x": 152.0,
            "y": 177.0
          },
          {
            "x": 159.0,
            "y": 177.0
          },
          {
            "x": 160.0,
            "y": 176.0
          },
          {
            "x": 164.0,
            "y": 175.0
          },
          {
            "x": 166.0,
            "y": 173.0
          },
          {
            "x": 168.0,
            "y": 169.0
          },
          {
            "x": 168.0,
            "y": 161.0
          },
          {
            "x": 167.0,
            "y": 160.0
          },
          {
            "x": 167.0,
            "y": 158.0
          },
          {
            "x": 163.0,
            "y": 155.0
          },
          {
            "x": 152.0,
            "y": 155.0
          },
          {
            "x": 149.0,
            "y": 158.0
          },
          {
            "x": 148.0,
            "y": 158.0
          }
        ]
      }
    },
    {
      "bounding_box": {
        "h": 6.0,
        "w": 8.0,
        "x": 148.0,
        "y": 146.0
      },
      "id": "2f0e455d-b952-4e05-9735-28ebd5856500",
      "name": "Leaf",
      "polygon": {
        "path": [
          {
            "x": 148.0,
            "y": 147.0
          },
          {
            "x": 148.0,
            "y": 149.0
          },
          {
            "x": 149.0,
            "y": 149.0
          },
          {
            "x": 152.0,
            "y": 152.0
          },
          {
            "x": 155.0,
            "y": 152.0
          },
          {
            "x": 156.0,
            "y": 151.0
          },
          {
            "x": 156.0,
            "y": 148.0
          },
          {
            "x": 153.0,
            "y": 146.0
          },
          {
            "x": 149.0,
            "y": 146.0
          }
        ]
      }
    }
  ],
  "dataset": "leafSegmentationPhenovator",
  "image": {
    "filename": "32-20-new_Tray-3x3_096-FC1-FcParamImage-Fmp_7.png",
    "height": 266,
    "original_filename": "32-20-new_Tray-3x3_096-FC1-FcParamImage-Fmp_7.png",
    "path": "/",
    "thumbnail_url": "https://darwin.v7labs.com/api/images/448097739/thumbnail",
    "url": "https://darwin.v7labs.com/api/images/448097739/original",
    "width": 266,
    "workview_url": "https://darwin.v7labs.com/workview?dataset=470301&image=441"
  }
}